setup.py
pyuiautomator/__init__.py
pyuiautomator/client.py
pyuiautomator.egg-info/PKG-INFO
pyuiautomator.egg-info/SOURCES.txt
pyuiautomator.egg-info/dependency_links.txt
pyuiautomator.egg-info/not-zip-safe
pyuiautomator.egg-info/requires.txt
pyuiautomator.egg-info/top_level.txt