Metadata-Version: 1.0
Name: pyuiautomator
Version: 1.3
Summary: uiautomator
Home-page: https://github.com/SuperMan42
Author: hpw123
Author-email: hpw15101048214@gmail.com
License: UNKNOWN
Keywords: uiautomator
Platform: UNKNOWN
